{"assets/audio/birds.mp3":["assets/audio/birds.mp3"],"assets/audio/heavyrain.mp3":["assets/audio/heavyrain.mp3"],"assets/audio/oceansound.mp3":["assets/audio/oceansound.mp3"],"assets/audio/winterstorm.mp3":["assets/audio/winterstorm.mp3"],"assets/images/angry.png":["assets/images/angry.png"],"assets/images/anxiety.png":["assets/images/anxiety.png"],"assets/images/happy.png":["assets/images/happy.png"],"assets/images/happyimo.png":["assets/images/happyimo.png"],"assets/images/homescreen.png":["assets/images/homescreen.png"],"assets/images/mangeBreath.png":["assets/images/mangeBreath.png"],"assets/images/pepole.png":["assets/images/pepole.png"],"assets/images/sad.png":["assets/images/sad.png"],"assets/images/smile.png":["assets/images/smile.png"],"assets/images/talk.jpg":["assets/images/talk.jpg"],"assets/images/topimg.png":["assets/images/topimg.png"],"assets/images/welcomebackground.png":["assets/images/welcomebackground.png"],"assets/images/welcomeimage.png":["assets/images/welcomeimage.png"],"packages/cupertino_icons/assets/CupertinoIcons.ttf":["packages/cupertino_icons/assets/CupertinoIcons.ttf"],"packages/dash_chat_2/assets/placeholder.png":["packages/dash_chat_2/assets/placeholder.png"],"packages/dash_chat_2/assets/profile_placeholder.png":["packages/dash_chat_2/assets/profile_placeholder.png"]}